LatentBoostClassifier/__init__.py
LatentBoostClassifier/model.py
LatentBoostClassifier/train.py
LatentBoostClassifier/visualize.py
LatentBoostClassifier-1.2.4.dist-info/LICENSE
LatentBoostClassifier-1.2.4.dist-info/METADATA
LatentBoostClassifier-1.2.4.dist-info/WHEEL
LatentBoostClassifier-1.2.4.dist-info/top_level.txt
LatentBoostClassifier-1.2.4.dist-info/RECORD
