Metadata-Version: 2.1
Name: LatentBoostClassifier
Version: 1.2.4
Summary: A hybrid generative model combining CVAE, CGAN, and Random Forest.
Home-page: https://github.com/AliBavarchee/LatentBoostClassifier
Author: Ali Bavarchee
Author-email: ali.bavarchee@gmail.com
License: MIT
Project-URL: Documentation, https://github.com/AliBavarchee/LatentBoostClassifier#readme
Project-URL: Source, https://github.com/AliBavarchee/LatentBoostClassifier
Project-URL: Tracker, https://github.com/AliBavarchee/LatentBoostClassifier/issues
Keywords: machine learning generative models CVAE CGAN Random Forest
Classifier: Programming Language :: Python :: 3.7
Classifier: License :: OSI Approved :: MIT License
Classifier: Operating System :: OS Independent
Classifier: Development Status :: 4 - Beta
Classifier: Topic :: Scientific/Engineering :: Artificial Intelligence
Requires-Python: >=3.7
License-File: LICENSE
Requires-Dist: tensorflow >=2.8.0
Requires-Dist: keras-tuner >=1.1.0
Requires-Dist: scikit-learn >=1.0
Requires-Dist: matplotlib >=3.4
Requires-Dist: seaborn >=0.11
Requires-Dist: numpy >=1.19
Requires-Dist: pandas >=1.1
Requires-Dist: tqdm >=4.62
